[
  {
    "page_number": 0,
    "bbox": [
      218.16,
      52.22,
      251.64,
      62.18
    ],
    "text": "( 285 )",
    "fonts": [
      "Times-Roman"
    ],
    "sizes": [
      8.485286712646484,
      9.482088088989258
    ]
  },
  {
    "page_number": 0,
    "bbox": [
      66.24,
      72.86,
      402.35,
      82.82
    ],
    "text": "A C C O U N T S A N D OPERATIONS OF T H E C E N T R A L B A N K",
    "fonts": [
      "Times-Bold"
    ],
    "sizes": [
      9.058221817016602,
      9.181676864624023,
      9.217775344848633,
      9.258809089660645,
      9.482088088989258
    ]
  },
  {
    "page_number": 0,
    "bbox": [
      54.0,
      95.18,
      415.11,
      129.14
    ],
    "text": "Financial accounts of the Central Bank for the year 1968 are given in Table 6 in Appendix II. The main changes in comparison with 1967 as at the end of December, 1968, were;",
    "fonts": [
      "Times-Roman"
    ],
    "sizes": [
      9.312847137451172,
      9.37042236328125,
      9.482088088989258
    ]
  },
  {
    "page_number": 0,
    "bbox": [
      60.96,
      192.55,
      156.62,
      217.25
    ],
    "text": "Total Demand Liabilities Currency circulation Demand Deposits",
    "fonts": [
      "Times-Bold"
    ],
    "sizes": [
      8.102740287780762,
      8.162313461303711,
      8.24756908416748,
      8.36514663696289,
      8.428523063659668
    ]
  },
  {
    "page_number": 0,
    "bbox": [
      61.2,
      216.79,
      178.97,
      241.49
    ],
    "text": "(of which commercial banks) International Reserve Domestic Assets",
    "fonts": [
      "Times-Bold"
    ],
    "sizes": [
      7.673330307006836,
      8.206611633300781,
      8.219002723693848,
      8.370997428894043,
      8.428523063659668
    ]
  },
  {
    "page_number": 0,
    "bbox": [
      68.88,
      241.03,
      223.68,
      257.81
    ],
    "text": "(of which Government and Government Guaranteed Securities)",
    "fonts": [
      "Times-Bold"
    ],
    "sizes": [
      7.673330307006836,
      8.21639347076416,
      8.428523063659668
    ]
  },
  {
    "page_number": 0,
    "bbox": [
      326.16,
      152.95,
      366.76,
      161.81
    ],
    "text": "CHANGE",
    "fonts": [
      "Times-Bold"
    ],
    "sizes": [
      8.213549613952637
    ]
  },
  {
    "page_number": 0,
    "bbox": [
      292.56,
      169.27,
      394.87,
      178.61
    ],
    "text": "Rs. million Percent",
    "fonts": [
      "Times-Bold"
    ],
    "sizes": [
      7.673330307006836,
      8.149248123168945,
      8.428523063659668
    ]
  },
  {
    "page_number": 0,
    "bbox": [
      300.96,
      191.83,
      398.18,
      241.49
    ],
    "text": "+ 273-2 + 14-8 + 9-1 + 0-8 + 192-7 + 27-0 \u2014 4-4 \u2014 3-0 \u2014 24-9 - 9 6 +294-2 + 16-8",
    "fonts": [
      "Times-Bold"
    ],
    "sizes": [
      7.673330307006836,
      8.063309669494629,
      8.105622291564941,
      8.428523063659668
    ]
  },
  {
    "page_number": 0,
    "bbox": [
      302.64,
      248.47,
      397.72,
      257.81
    ],
    "text": "+269-4 + 19-6",
    "fonts": [
      "Times-Bold"
    ],
    "sizes": [
      7.673330307006836,
      8.078693389892578
    ]
  },
  {
    "page_number": 0,
    "bbox": [
      104.16,
      270.55,
      314.52,
      279.89
    ],
    "text": "+Increase \u2014\u2022 Decrease",
    "fonts": [
      "Times-Bold"
    ],
    "sizes": [
      8.0,
      8.178879737854004,
      8.272672653198242
    ]
  },
  {
    "page_number": 0,
    "bbox": [
      56.64,
      290.3,
      415.96,
      312.5
    ],
    "text": "There were no changes during the year in the Central Bank's rates for Sterling, Indian Rupees and U.S. Dollars which were:-",
    "fonts": [
      "Times-Roman"
    ],
    "sizes": [
      9.38260269165039,
      9.412596702575684,
      9.482088088989258,
      9.738773345947266
    ]
  },
  {
    "page_number": 0,
    "bbox": [
      56.16,
      341.83,
      136.11,
      358.85
    ],
    "text": "Sterling (per Ceylon rupee)",
    "fonts": [
      "Times-Bold"
    ],
    "sizes": [
      7.673330307006836,
      8.193500518798828,
      8.35170841217041,
      8.428523063659668
    ]
  },
  {
    "page_number": 0,
    "bbox": [
      56.16,
      378.31,
      107.09,
      394.85
    ],
    "text": "Indian Rupees (per 100)",
    "fonts": [
      "Times-Bold",
      "Times-BoldItalic"
    ],
    "sizes": [
      7.673330307006836,
      8.324152946472168
    ]
  },
  {
    "page_number": 0,
    "bbox": [
      56.64,
      414.31,
      102.7,
      431.09
    ],
    "text": "U.S. Dollars (per 100)",
    "fonts": [
      "Times-Bold",
      "Times-BoldItalic"
    ],
    "sizes": [
      7.673330307006836,
      8.428523063659668
    ]
  },
  {
    "page_number": 0,
    "bbox": [
      156.24,
      341.83,
      224.82,
      366.77
    ],
    "text": "Spot Forward (upto six months)",
    "fonts": [
      "Times-Bold"
    ],
    "sizes": [
      8.062634468078613,
      8.2839994430542,
      8.357874870300293,
      8.428523063659668
    ]
  },
  {
    "page_number": 0,
    "bbox": [
      156.24,
      378.07,
      224.33,
      403.01
    ],
    "text": "Spot Forward (upto six months)",
    "fonts": [
      "Times-Bold"
    ],
    "sizes": [
      8.062634468078613,
      8.2839994430542,
      8.357874870300293,
      8.428523063659668
    ]
  },
  {
    "page_number": 0,
    "bbox": [
      156.24,
      414.55,
      224.71,
      439.25
    ],
    "text": "Spot Forward (upto six months)",
    "fonts": [
      "Times-Bold"
    ],
    "sizes": [
      8.062634468078613,
      8.2839994430542,
      8.357874870300293,
      8.428523063659668
    ]
  },
  {
    "page_number": 0,
    "bbox": [
      243.84,
      325.03,
      314.5,
      373.49
    ],
    "text": "T.T. Buying lsh. 4 53/64d. l/128d. per month discount against spot",
    "fonts": [
      "Times-Bold",
      "Times-BoldItalic",
      "Times-Roman"
    ],
    "sizes": [
      6.194789886474609,
      6.532105445861816,
      7.673330307006836,
      7.706869602203369,
      8.186232566833496,
      8.37118911743164,
      8.390890121459961,
      8.428523063659668
    ]
  },
  {
    "page_number": 0,
    "bbox": [
      244.08,
      377.59,
      315.8,
      431.33
    ],
    "text": "Rs. 79 1/8 1/32 of a rupee per month discount against spot Rs.592-25 Rs.592-25",
    "fonts": [
      "Times-Bold"
    ],
    "sizes": [
      7.673330307006836,
      8.056878089904785,
      8.299089431762695,
      8.332144737243652,
      8.428523063659668
    ]
  },
  {
    "page_number": 0,
    "bbox": [
      330.24,
      325.27,
      400.4,
      373.97
    ],
    "text": "T.T. Selling lsh. 4 13/16d. l/128d. per month premium against spot",
    "fonts": [
      "Times-Bold",
      "Times-BoldItalic",
      "Times-Roman"
    ],
    "sizes": [
      6.194789886474609,
      6.532105445861816,
      7.673330307006836,
      8.186232566833496,
      8.29079532623291,
      8.390890121459961,
      8.428523063659668
    ]
  },
  {
    "page_number": 0,
    "bbox": [
      325.92,
      377.83,
      403.51,
      394.85
    ],
    "text": ". Rs. 79 3/16 \u2022 1/32 of a rupee per",
    "fonts": [
      "Times-Bold"
    ],
    "sizes": [
      7.673330307006836,
      8.428523063659668
    ]
  },
  {
    "page_number": 0,
    "bbox": [
      330.0,
      394.15,
      392.58,
      410.93
    ],
    "text": "month premium against spot",
    "fonts": [
      "Times-Bold"
    ],
    "sizes": [
      8.299089431762695,
      8.332144737243652,
      8.428523063659668
    ]
  },
  {
    "page_number": 0,
    "bbox": [
      330.24,
      414.07,
      415.52,
      446.93
    ],
    "text": "Rs. 592.50 -/25 cents per month permium against spot",
    "fonts": [
      "Times-Bold"
    ],
    "sizes": [
      7.673330307006836,
      8.016223907470703,
      8.29079532623291,
      8.390890121459961,
      8.428523063659668
    ]
  },
  {
    "page_number": 0,
    "bbox": [
      56.88,
      459.5,
      417.0,
      483.62
    ],
    "text": "Foreign exchange transactions of the Central Bank are shown in Table 11 in Appendix II.",
    "fonts": [
      "Times-Roman"
    ],
    "sizes": [
      9.4204683303833,
      9.482088088989258
    ]
  },
  {
    "page_number": 0,
    "bbox": [
      57.12,
      495.74,
      417.82,
      649.7
    ],
    "text": "Commencing from May 6, 1968, the Central Bank's rates of interest on advances against Government Securities and against usance promissory notes relating to commercial and production loans were increased from 5 % to 5J per cent per annum. The rate of interest on Central Bank advances to com\u00admercial banks against the pledge of usance promissory notes in respect of ad\u00advances granted to Co-operative Societies to finance the purchase of paddy under the Guaranteed Price Scheme and for the purchase, sale or storage of locally grown Agricultural products remained unchanged at 3 per cent per annum. The rate of interest on the Central Bank's advances to commercial banks secured by the pledge of usance promissory notes of Co-operative Societies relating to the production of paddy, red onions, Bombay onions, chillies, potatoes, pineapples and vegetables was fixed at 1$ per cent per annum, provi\u00added that commercial banks which availed themselves of this facility did not",
    "fonts": [
      "Times-Roman"
    ],
    "sizes": [
      8.63249683380127,
      9.242128372192383,
      9.413457870483398,
      9.44789981842041,
      9.482088088989258,
      9.646052360534668,
      9.647772789001465,
      9.675607681274414,
      9.698267936706543,
      9.730786323547363,
      9.74272346496582
    ]
  },
  {
    "page_number": 1,
    "bbox": [
      214.56,
      52.28,
      259.78,
      62.47
    ],
    "text": "( 286 )",
    "fonts": [
      "Times-Roman"
    ],
    "sizes": [
      8.579068183898926,
      9.560919761657715
    ]
  },
  {
    "page_number": 1,
    "bbox": [
      58.32,
      72.68,
      415.82,
      118.87
    ],
    "text": "charge more than 8 per cent per annum (subject to a rebate of 3 per cent per annum if payment is made on the due date) from the makers of the promissory notes. The Central Bank's discount rate for Treasury Bills continued to be at 1/8 per cent per annum over the last accepted average tender rate.",
    "fonts": [
      "Times-Roman"
    ],
    "sizes": [
      9.145929336547852,
      9.560919761657715
    ]
  },
  {
    "page_number": 1,
    "bbox": [
      58.8,
      131.0,
      184.04,
      141.19
    ],
    "text": "Foreign Currency Notes",
    "fonts": [
      "Times-Bold"
    ],
    "sizes": [
      9.216315269470215,
      9.344002723693848,
      9.560919761657715
    ]
  },
  {
    "page_number": 1,
    "bbox": [
      58.56,
      147.32,
      416.92,
      181.99
    ],
    "text": "With effect from August 1968, arrangements were made for the Central Bank to purchase specified foreign currency notes from commercial banks operating in Ceylon at prescribed rates.",
    "fonts": [
      "Times-Roman"
    ],
    "sizes": [
      9.010272026062012,
      9.312562942504883,
      9.3643159866333,
      9.560919761657715
    ]
  },
  {
    "page_number": 1,
    "bbox": [
      59.28,
      193.64,
      184.39,
      203.83
    ],
    "text": "Credit Guarantee Scheme",
    "fonts": [
      "Times-Bold"
    ],
    "sizes": [
      9.297964096069336,
      9.304970741271973,
      9.560919761657715
    ]
  },
  {
    "page_number": 1,
    "bbox": [
      59.52,
      210.2,
      418.21,
      292.39
    ],
    "text": "Under this Scheme, the Central Bank on behalf of the Government, guarantees payment upto 75 per cent of the amount in default in respect of loans granted by commercial banks to Co-operative Societies for the purpose of culti\u00advation of paddy, red onions, Bombay onions, chillies, potatoes, pineapples and vegetables. A guarantee fee of one half of one per cent is payable by the commercial banks. As at December 31st, 1968, the Central Bank had guaranteed loans granted by commercial banks totalling Rs. 75,633,000.",
    "fonts": [
      "Times-Roman"
    ],
    "sizes": [
      9.062956809997559,
      9.238558769226074,
      9.339472770690918,
      9.344274520874023,
      9.507477760314941,
      9.51779842376709,
      9.560919761657715,
      9.838237762451172,
      9.84099006652832
    ]
  },
  {
    "page_number": 1,
    "bbox": [
      60.72,
      305.0,
      208.13,
      315.19
    ],
    "text": "Medium and long term credit",
    "fonts": [
      "Times-Bold"
    ],
    "sizes": [
      9.252840995788574,
      9.319740295410156,
      9.527220726013184,
      9.560919761657715
    ]
  },
  {
    "page_number": 1,
    "bbox": [
      60.48,
      321.32,
      418.83,
      379.51
    ],
    "text": "During the year, credit institutions made increased use of the Bank's medium and long term refinance facilities. Refinance loans totalling Rs. 5,228,000 were, granted to credit institutions during the year. The rates of interest on refinance loans granted by the Central Bank were revised on November 1st, 1968 as follows:-",
    "fonts": [
      "Times-Roman"
    ],
    "sizes": [
      9.108139038085938,
      9.168481826782227,
      9.349617004394531,
      9.560919761657715,
      9.846492767333984
    ]
  },
  {
    "page_number": 1,
    "bbox": [
      84.48,
      391.88,
      418.34,
      414.55
    ],
    "text": "(a) for the promotion or development of Agriculture or industry - 4 per cent per annum;",
    "fonts": [
      "Times-Bold",
      "Times-Italic",
      "Times-Roman"
    ],
    "sizes": [
      8.885457038879395,
      9.309608459472656,
      9.408455848693848,
      9.560919761657715
    ]
  },
  {
    "page_number": 1,
    "bbox": [
      84.48,
      420.2,
      418.14,
      454.87
    ],
    "text": "(b) for the modernisation of tea factories and/or for the construction of new tea factories where the Tea Controller meets a part of the interest payable on such loans-",
    "fonts": [
      "Times-Italic",
      "Times-Roman"
    ],
    "sizes": [
      8.965682029724121,
      9.560919761657715,
      9.821921348571777
    ]
  },
  {
    "page_number": 1,
    "bbox": [
      122.64,
      462.68,
      418.93,
      484.87
    ],
    "text": "(i) 5 per cent perannum in respect of refinance loans to cover the local costs;",
    "fonts": [
      "Times-Roman"
    ],
    "sizes": [
      8.997910499572754,
      9.388057708740234,
      9.560919761657715
    ]
  },
  {
    "page_number": 1,
    "bbox": [
      121.2,
      490.76,
      419.41,
      513.19
    ],
    "text": "(ii) 7 per cent per annum in respect of refinance loans to cover the foreign exchange costs;",
    "fonts": [
      "Times-Italic",
      "Times-Roman"
    ],
    "sizes": [
      8.990005493164062,
      9.00171947479248,
      9.072524070739746,
      9.560919761657715
    ]
  },
  {
    "page_number": 1,
    "bbox": [
      84.96,
      518.84,
      417.86,
      541.27
    ],
    "text": "(c) for the promotion or development of trade, commerce or business-5^ per cent per annum.",
    "fonts": [
      "Times-Italic",
      "Times-Roman"
    ],
    "sizes": [
      8.958834648132324,
      9.560919761657715
    ]
  },
  {
    "page_number": 1,
    "bbox": [
      60.96,
      552.44,
      137.83,
      562.63
    ],
    "text": "Currency Issue",
    "fonts": [
      "Times-Bold"
    ],
    "sizes": [
      9.216315269470215,
      9.560919761657715
    ]
  },
  {
    "page_number": 1,
    "bbox": [
      60.96,
      569.24,
      419.59,
      603.43
    ],
    "text": "At the end of 1968 the total currency circulation stood at Rs. 1,181.9 million, an increase of Rs. 109.1 million over the figure as at the end of 1967. Notes in circulation increased by Rs. 104.6 million and coins by Rs. 4-5 million.",
    "fonts": [
      "Times-Roman"
    ],
    "sizes": [
      9.113388061523438,
      9.348756790161133,
      9.5169095993042,
      9.534591674804688,
      9.560919761657715
    ]
  },
  {
    "page_number": 1,
    "bbox": [
      60.48,
      615.32,
      419.33,
      649.51
    ],
    "text": "A new cupro nickel coin of the denomination of Rs- 2 was issued in October, 1968, in connection with the Special Food and Agriculture Organi\u00adsation Coin Issue. This coin is..round, has a diameter of 1,240 inches and",
    "fonts": [
      "Times-Roman"
    ],
    "sizes": [
      9.335529327392578,
      9.498927116394043,
      9.560919761657715
    ]
  },
  {
    "page_number": 2,
    "bbox": [
      214.08,
      46.52,
      247.09,
      56.71
    ],
    "text": "( 287 )",
    "fonts": [
      "Times-Roman"
    ],
    "sizes": [
      8.579068183898926,
      9.605081558227539
    ]
  },
  {
    "page_number": 2,
    "bbox": [
      49.68,
      66.68,
      410.08,
      172.87
    ],
    "text": "weighs 190 grains. On the obverse of the coin is a reproduction of the statue at Polonnaruwa traditionally believed to be that of King Parakrama Bahu the Great, with a design consisting of ears of paddy on either side and a paddy basket at the bottom. The legend \"Grow More Food\" appears in Sinhala, Tamil and English near the periphery of the coin. On the reverse a large figure '2' appears in the centre and the value Rupees Two in words in Sinhala, Tamil and English appears across the figure 2. The words Sri Lanka in Sinhala appear above the figure 2 while the Tamil and English versions flank it on the left and right respectively. The year of issue 1968, appears below the figure 2.",
    "fonts": [
      "Times-Roman"
    ],
    "sizes": [
      9.010272026062012,
      9.510814666748047,
      9.566849708557129,
      9.572952270507812,
      9.578608512878418,
      9.605081558227539,
      9.767956733703613,
      9.85031795501709
    ]
  },
  {
    "page_number": 2,
    "bbox": [
      49.44,
      185.48,
      407.19,
      207.67
    ],
    "text": "The coin is in Circulation along with the note of the same deno\u00admination.",
    "fonts": [
      "Times-Roman"
    ],
    "sizes": [
      9.447643280029297,
      9.605081558227539
    ]
  },
  {
    "page_number": 2,
    "bbox": [
      48.96,
      219.56,
      298.66,
      229.75
    ],
    "text": "Foreign Exchange Entitlement Certificates Scheme",
    "fonts": [
      "Times-Bold"
    ],
    "sizes": [
      9.263718605041504,
      9.344002723693848,
      9.351019859313965,
      9.605081558227539
    ]
  },
  {
    "page_number": 2,
    "bbox": [
      49.68,
      238.04,
      410.01,
      272.23
    ],
    "text": "In terms of the Foreign Exchange Entitlement Certificates Act No. 28 of 1968, the Central Bank of Ceylon administers the Foreign Exchange Entitlement Certificates Scheme on behalf of the Government of Ceylon.",
    "fonts": [
      "Times-Roman"
    ],
    "sizes": [
      9.010272026062012,
      9.339472770690918,
      9.477474212646484,
      9.575780868530273,
      9.605081558227539
    ]
  },
  {
    "page_number": 2,
    "bbox": [
      49.92,
      284.12,
      172.5,
      294.31
    ],
    "text": "Income and Expenditure",
    "fonts": [
      "Times-Bold"
    ],
    "sizes": [
      9.3203763961792,
      9.395673751831055,
      9.605081558227539
    ]
  },
  {
    "page_number": 2,
    "bbox": [
      49.92,
      302.36,
      410.09,
      360.55
    ],
    "text": "The income of the Central Bank for the year amounted to Rs. 33,458,000 and expenditure, including allocations to reserves and provision for depreciation of the value of the Bank Building, amounted to Rs. 32,458,000. The net profit of Rs, 1,000,000 was carried to Surplus in terms of Section 39(b) of the Monetary Law Act.",
    "fonts": [
      "Times-Roman"
    ],
    "sizes": [
      8.83276653289795,
      9.062956809997559,
      9.104002952575684,
      9.108139038085938,
      9.142180442810059,
      9.26102352142334,
      9.447643280029297,
      9.484748840332031,
      9.605081558227539
    ]
  },
  {
    "page_number": 2,
    "bbox": [
      49.92,
      372.92,
      137.2,
      383.11
    ],
    "text": "Bank Supervision",
    "fonts": [
      "Times-Bold"
    ],
    "sizes": [
      9.268789291381836,
      9.605081558227539
    ]
  },
  {
    "page_number": 2,
    "bbox": [
      50.4,
      391.16,
      410.27,
      437.35
    ],
    "text": "In the year 1968 the Department of Bank Supervision examined seven commercial banks under Section 29(1) of the Monetary Law Act. The Depart\u00adment continued to perform functions connected with the operation of Part III of the Finance Act No. 65 of 1961.",
    "fonts": [
      "Times-Roman"
    ],
    "sizes": [
      8.83276653289795,
      9.028523445129395,
      9.507477760314941,
      9.575780868530273,
      9.605081558227539,
      9.8053617477417
    ]
  },
  {
    "page_number": 2,
    "bbox": [
      50.64,
      449.24,
      410.56,
      483.43
    ],
    "text": "The Development Finance Division was engaged in the appraisal of Tea Factory Modernisation projects in connection with the line of credit made available to the Central Bank by the Asian Development Bank.",
    "fonts": [
      "Times-Roman"
    ],
    "sizes": [
      9.447643280029297,
      9.468002319335938,
      9.545903205871582,
      9.605081558227539
    ]
  }
]